inferia/__init__.py
inferia/cli.py
inferia/api/__init__.py
inferia/api/handlers.py
inferia/api/responses.py
inferia/commands/__init__.py
inferia/commands/initialize.py
inferia/commands/run.py
inferia/commands/scaffold_predict.py
inferia/core/__init__.py
inferia/core/app.py
inferia/core/config.py
inferia/core/exceptioin_handlers.py
inferia/core/exceptions.py
inferia/core/logging.py
inferia/core/metrics.py
inferia/core/model_store.py
inferia/core/models.py
inferia/core/utils.py
inferia/templates/predict_class_template.jinja2
inferia-0.2.1.dist-info/LICENSE
inferia-0.2.1.dist-info/METADATA
inferia-0.2.1.dist-info/WHEEL
inferia-0.2.1.dist-info/entry_points.txt
inferia-0.2.1.dist-info/top_level.txt
inferia-0.2.1.dist-info/RECORD
