Metadata-Version: 2.2
Name: inferia
Version: 0.2.1
Summary: Inferia is a Python module designed to streamline the creation and deployment of inference services. It provides tools and abstractions to wrap machine learning models and expose them as robust, production-ready APIs with minimal effort.
Author-email: freepik-company/tech-avengers <aivengers@freepik.com>
Project-URL: Homepage, https://github.com/freepik-company/fc-py-inferia
Project-URL: Issues, https://github.com/freepik-company/fc-py-inferia/issues
Classifier: Programming Language :: Python :: 3
Classifier: License :: OSI Approved :: MIT License
Classifier: Operating System :: OS Independent
Requires-Python: >=3.10
License-File: LICENSE
Requires-Dist: click>=8.1.8
Requires-Dist: fastapi>=0.115.6
Requires-Dist: google-cloud-storage>=2.19.0
Requires-Dist: huggingface-hub>=0.27.1
Requires-Dist: jinja2>=3.1.5
Requires-Dist: opentelemetry-exporter-prometheus>=0.50b0
Requires-Dist: opentelemetry-instrumentation-fastapi>=0.50b0
Requires-Dist: opentelemetry-sdk>=1.29.0
Requires-Dist: prometheus-client>=0.21.1
Requires-Dist: pydantic>=2.10.5
Requires-Dist: pyyaml>=6.0.2
Requires-Dist: structlog>=25.1.0
Requires-Dist: uvicorn>=0.34.0
